assignment_1.v

module testbench;
	reg D,CLK,RST;
	wire Q;

	dff flipflop(D,CLK,RST,Q);

	// Testing

	initial begin
		CLK = 1;
		D = 0;
		RST = 1;
		$dumpfile("D.vcd");
		$dumpvars(0,flipflop);
		
		#1 D = 1;
		#3 RST = 0;
		#8 D = 0;
		#6 D = 1;
		#2 D = 0;
		#6 D = 1;
		#5 D = 0;
		#3 RST = 1;
		#10 $finish;
		
	end

	always #5 CLK = ~CLK;

endmodule


module dff(d, clk, reset, q);

input d,clk,reset;
output reg q;

always @(posedge clk or posedge reset)
begin

	if (reset == 1'b1)
	begin
		q <= 0;
	end 
	else
	begin
		q <= d;
	end
	
end
endmodule

D.vcd
$date
	Thu May 17 13:58:25 2018
$end
$version
	Icarus Verilog
$end
$timescale
	1s
$end
$scope module testbench $end
$scope module flipflop $end
$var wire 1 ! clk $end
$var wire 1 " d $end
$var wire 1 # reset $end
$var reg 1 $ q $end
$upscope $end
$upscope $end
$enddefinitions $end
#0
$dumpvars
0$
1#
0"
1!
$end
#1
1"
#4
0#
#5
0!
#10
1$
1!
#12
0"
#15
0!
#18
1"
#20
0$
0"
1!
#25
0!
#26
1"
#30
1$
1!
#31
0"
#34
0$
1#
