SR_Latches/enabled_SR_Latch.v
module Enabled_SR_Latch(S,R,Q,Qbar,En);
	input S,R,En;
	output Q,Qbar;
	wire x1,x2;
	
	nand n1(x1,S,En);
	nand n2(x2,En,R);
	nand n3(Q,Qbar,x1);
	nand n4(Qbar,x2,Q);
	
endmodule


module sr_latch_testbench;
	reg S,R,En ;//,Q,Qbar;
	wire Q,Qbar;
	Enabled_SR_Latch srl(S,R,Q,Qbar,En);
	
	initial begin
	
		//always #3 En = ~En;
		En = 1;
		$monitor($time , "  S = %b, R = %b, En = %d , Q = %b, Q' = %b",S,R,En,Q,Qbar);
		$dumpfile("Enabled_SR_Latch.vcd");
		$dumpvars(0,srl);
		//Q = 1; Qbar = 0;
		#1 S = 1; R = 0;
		#2 S = 0; R = 0;
		#1 S = 0; R = 1;
		#2 S = 0; R = 0;
		#3 S = 1; R = 0;
		#4 S = 0; R = 1;
		#1 S = 0; R = 0;
		#1 S = 0; R = 0;
		$finish;
	
	end
		always #1 En = ~En;

endmodule

SR_Latches/Enabled_SR_Latch.vcd
$date
	Sun May 27 12:52:18 2018
$end
$version
	Icarus Verilog
$end
$timescale
	1s
$end
$scope module sr_latch_testbench $end
$scope module srl $end
$var wire 1 ! En $end
$var wire 1 " Q $end
$var wire 1 # Qbar $end
$var wire 1 $ R $end
$var wire 1 % S $end
$var wire 1 & x1 $end
$var wire 1 ' x2 $end
$upscope $end
$upscope $end
$enddefinitions $end
#0
$dumpvars
x'
x&
x%
x$
x#
x"
1!
$end
#1
1'
1&
0!
0$
1%
#2
0#
1"
0&
1!
#3
1&
0!
0%
#4
0"
1#
0'
1!
1$
#5
1'
0!
#6
1!
0$
#7
0!
#8
1!
#9
0!
1%
#10
0#
1"
0&
1!
#11
1&
0!
#12
0&
1!
#13
1&
0!
1$
0%
#14
1!
0$
#15
0!
